CHANGELOG.md
MANIFEST.in
README.rst
setup.cfg
setup.py
docs/Makefile
docs/conf.py
docs/index.rst
docs/installation.rst
docs/make.bat
docs/usage.rst
test_report_processor/__init__.py
test_report_processor/constants.py
test_report_processor/test_report_processor.py
test_report_processor.egg-info/PKG-INFO
test_report_processor.egg-info/SOURCES.txt
test_report_processor.egg-info/dependency_links.txt
test_report_processor.egg-info/not-zip-safe
test_report_processor.egg-info/requires.txt
test_report_processor.egg-info/top_level.txt