Metadata-Version: 1.1
Name: test-report-processor
Version: 0.10.8
Summary: This package parses a cucumber JSON to a report friendly JSON
Home-page: https://git.kpn.org/projects/DE/repos/test-report-processor
Author: Rein van der Vegt
Author-email: reinier.vandervegt@kpn.com
License: UNKNOWN
Platform: UNKNOWN
Classifier: Development Status :: 5 - Production/Stable
Classifier: Environment :: Web Environment
Classifier: Intended Audience :: Developers
Classifier: Operating System :: OS Independent
Classifier: Programming Language :: Python
Classifier: Programming Language :: Python :: 2
Classifier: Programming Language :: Python :: 2.7
Classifier: Programming Language :: Python :: 3
Classifier: Programming Language :: Python :: 3.5
Classifier: Programming Language :: Python :: 3.6
Classifier: Topic :: Internet :: WWW/HTTP
